ascii_art/__init__.py
ascii_art/__main__.py
ascii_art/core.py
ascii_me_cli-0.1.4.dist-info/licenses/LICENSE
ascii_me_cli-0.1.4.dist-info/METADATA
ascii_me_cli-0.1.4.dist-info/WHEEL
ascii_me_cli-0.1.4.dist-info/entry_points.txt
ascii_me_cli-0.1.4.dist-info/top_level.txt
ascii_me_cli-0.1.4.dist-info/RECORD
