Metadata-Version: 2.4
Name: ascii-me-cli
Version: 0.1.4
Summary: Convierte imágenes y GIFs en animaciones ASCII en la terminal
Home-page: https://github.com/WetZap/Ascii-Me
Author: WetZap
Author-email: jorgerlvdg2016@gmail.com
Classifier: Programming Language :: Python :: 3
Classifier: Operating System :: OS Independent
Classifier: Topic :: Multimedia :: Graphics
Classifier: Topic :: Terminals
Requires-Python: >=3.7
License-File: LICENSE
Requires-Dist: Pillow>=9.0.0
Dynamic: author
Dynamic: author-email
Dynamic: classifier
Dynamic: description
Dynamic: description-content-type
Dynamic: home-page
Dynamic: license-file
Dynamic: requires-dist
Dynamic: requires-python
Dynamic: summary
